pystreamhandler/__init__.py
pystreamhandler/handlers.py
pystreamhandler-1.0.0.dist-info/licenses/LICENSE
pystreamhandler-1.0.0.dist-info/METADATA
pystreamhandler-1.0.0.dist-info/WHEEL
pystreamhandler-1.0.0.dist-info/top_level.txt
pystreamhandler-1.0.0.dist-info/RECORD
