Metadata-Version: 2.4
Name: PyStreamHandler
Version: 1.0.0
Summary: PyStreamHandler is a lightweight Python package designed to facilitate reading and writing binary data from buffers using Python's built-in `struct` module and `bytearray`.
Home-page: https://www.github.com/hansenchristoffer/pystreamhandler
Author: Christoffer Hansen
Author-email: Christoffer Hansen <chris.hansen.ch@outlook.com>
Maintainer-email: Christoffer Hansen <chris.hansen.ch@outlook.com>
Project-URL: Homepage, https://github.com/hansenchristoffer/PyStreamHandler
Project-URL: Repository, https://github.com/hansenchristoffer/PyStreamHandler.git
Project-URL: Changelog, https://github.com/hansenchristoffer/PyStreamHandler/blob/master/CHANGELOG.md
Keywords: binary,stream,utility
Classifier: Programming Language :: Python :: 3
Classifier: License :: OSI Approved :: MIT License
Classifier: Operating System :: OS Independent
Requires-Python: >=3.6
License-File: LICENSE
Dynamic: author
Dynamic: home-page
Dynamic: license-file
Dynamic: requires-python
